gradio_pointcloudeditor/__init__.py
gradio_pointcloudeditor/pointcloudeditor.py
gradio_pointcloudeditor/pointcloudeditor.pyi
gradio_pointcloudeditor/templates/component/index.js
gradio_pointcloudeditor/templates/component/style.css
gradio_pointcloudeditor/templates/example/index.js
gradio_pointcloudeditor/templates/example/style.css
gradio_pointcloudeditor-0.0.9.dist-info/METADATA
gradio_pointcloudeditor-0.0.9.dist-info/WHEEL
gradio_pointcloudeditor-0.0.9.dist-info/RECORD
